{"trial_id": "0021", "hyperparameters": {"space": [{"class_name": "Int", "config": {"name": "intermediate_dim1", "default": null, "conditions": [], "min_value": 32, "max_value": 512, "step": 32, "sampling": "linear"}}, {"class_name": "Float", "config": {"name": "dropout1", "default": 0.1, "conditions": [], "min_value": 0.1, "max_value": 0.8, "step": null, "sampling": "log"}}, {"class_name": "Int", "config": {"name": "intermediate_dim2", "default": null, "conditions": [], "min_value": 32, "max_value": 512, "step": 32, "sampling": "linear"}}, {"class_name": "Float", "config": {"name": "dropout2", "default": 0.1, "conditions": [], "min_value": 0.1, "max_value": 0.8, "step": null, "sampling": "log"}}, {"class_name": "Int", "config": {"name": "intermediate_dim3", "default": null, "conditions": [], "min_value": 32, "max_value": 512, "step": 32, "sampling": "linear"}}, {"class_name": "Float", "config": {"name": "dropout3", "default": 0.1, "conditions": [], "min_value": 0.1, "max_value": 0.8, "step": null, "sampling": "log"}}, {"class_name": "Float", "config": {"name": "rate", "default": 0.1, "conditions": [], "min_value": 0.1, "max_value": 0.8, "step": null, "sampling": "log"}}, {"class_name": "Float", "config": {"name": "lr", "default": 0.0001, "conditions": [], "min_value": 0.0001, "max_value": 0.01, "step": null, "sampling": "log"}}, {"class_name": "Float", "config": {"name": "weight_decay", "default": 0.0001, "conditions": [], "min_value": 0.0001, "max_value": 0.01, "step": null, "sampling": "log"}}], "values": {"intermediate_dim1": 320, "dropout1": 0.5407954531880822, "intermediate_dim2": 96, "dropout2": 0.4190329942231431, "intermediate_dim3": 128, "dropout3": 0.15796203606295922, "rate": 0.4321826017608931, "lr": 0.00477040242246797, "weight_decay": 0.002383170993373952, "tuner/epochs": 2, "tuner/initial_epoch": 0, "tuner/bracket": 3, "tuner/round": 0}}, "metrics": {"metrics": {"loss": {"direction": "min", "observations": [{"value": [1581015552.0], "step": 1}]}, "r2_score": {"direction": "min", "observations": [{"value": [-0.2346128523349762], "step": 1}]}, "mean_squared_error": {"direction": "min", "observations": [{"value": [1581015552.0], "step": 1}]}, "mean_absolute_error": {"direction": "min", "observations": [{"value": [11817.8134765625], "step": 1}]}, "mean_absolute_percentage_error": {"direction": "min", "observations": [{"value": [86.37409973144531], "step": 1}]}, "mean_squared_logarithmic_error": {"direction": "min", "observations": [{"value": [8.315661430358887], "step": 1}]}, "root_mean_squared_error": {"direction": "min", "observations": [{"value": [39761.984375], "step": 1}]}, "acc": {"direction": "max", "observations": [{"value": [0.0], "step": 1}]}, "val_loss": {"direction": "min", "observations": [{"value": [1338930944.0], "step": 1}]}, "val_r2_score": {"direction": "min", "observations": [{"value": [-0.25845104455947876], "step": 1}]}, "val_mean_squared_error": {"direction": "min", "observations": [{"value": [1338930944.0], "step": 1}]}, "val_mean_absolute_error": {"direction": "min", "observations": [{"value": [10461.9794921875], "step": 1}]}, "val_mean_absolute_percentage_error": {"direction": "min", "observations": [{"value": [76.053955078125], "step": 1}]}, "val_mean_squared_logarithmic_error": {"direction": "min", "observations": [{"value": [5.275674819946289], "step": 1}]}, "val_root_mean_squared_error": {"direction": "min", "observations": [{"value": [36591.40625], "step": 1}]}, "val_acc": {"direction": "max", "observations": [{"value": [0.0], "step": 1}]}, "multi_objective": {"direction": "min", "observations": [{"value": [1338930944.0], "step": 1}]}}}, "score": 1338930944.0, "best_step": 1, "status": "COMPLETED", "message": null}