{"trial_id": "0050", "hyperparameters": {"space": [{"class_name": "Int", "config": {"name": "intermediate_dim1", "default": null, "conditions": [], "min_value": 32, "max_value": 512, "step": 32, "sampling": "linear"}}, {"class_name": "Float", "config": {"name": "dropout1", "default": 0.1, "conditions": [], "min_value": 0.1, "max_value": 0.8, "step": null, "sampling": "log"}}, {"class_name": "Int", "config": {"name": "intermediate_dim2", "default": null, "conditions": [], "min_value": 32, "max_value": 512, "step": 32, "sampling": "linear"}}, {"class_name": "Float", "config": {"name": "dropout2", "default": 0.1, "conditions": [], "min_value": 0.1, "max_value": 0.8, "step": null, "sampling": "log"}}, {"class_name": "Int", "config": {"name": "intermediate_dim3", "default": null, "conditions": [], "min_value": 32, "max_value": 512, "step": 32, "sampling": "linear"}}, {"class_name": "Float", "config": {"name": "dropout3", "default": 0.1, "conditions": [], "min_value": 0.1, "max_value": 0.8, "step": null, "sampling": "log"}}, {"class_name": "Float", "config": {"name": "rate", "default": 0.1, "conditions": [], "min_value": 0.1, "max_value": 0.8, "step": null, "sampling": "log"}}, {"class_name": "Float", "config": {"name": "lr", "default": 0.0001, "conditions": [], "min_value": 0.0001, "max_value": 0.01, "step": null, "sampling": "log"}}, {"class_name": "Float", "config": {"name": "weight_decay", "default": 0.0001, "conditions": [], "min_value": 0.0001, "max_value": 0.01, "step": null, "sampling": "log"}}], "values": {"intermediate_dim1": 256, "dropout1": 0.49018580243115323, "intermediate_dim2": 448, "dropout2": 0.714416718332803, "intermediate_dim3": 96, "dropout3": 0.20680425973435917, "rate": 0.14357592839421485, "lr": 0.006779402365887434, "weight_decay": 0.003402167358619979, "tuner/epochs": 4, "tuner/initial_epoch": 0, "tuner/bracket": 2, "tuner/round": 0}}, "metrics": {"metrics": {"loss": {"direction": "min", "observations": [{"value": [2312281088.0], "step": 3}]}, "r2_score": {"direction": "min", "observations": [{"value": [-0.11659643054008484], "step": 3}]}, "mean_squared_error": {"direction": "min", "observations": [{"value": [2312281088.0], "step": 3}]}, "mean_absolute_error": {"direction": "min", "observations": [{"value": [10759.109375], "step": 3}]}, "mean_absolute_percentage_error": {"direction": "min", "observations": [{"value": [116.89551544189453], "step": 3}]}, "mean_squared_logarithmic_error": {"direction": "min", "observations": [{"value": [1.7395294904708862], "step": 3}]}, "root_mean_squared_error": {"direction": "min", "observations": [{"value": [48086.18359375], "step": 3}]}, "acc": {"direction": "max", "observations": [{"value": [0.0], "step": 3}]}, "val_loss": {"direction": "min", "observations": [{"value": [5622792704.0], "step": 3}]}, "val_r2_score": {"direction": "min", "observations": [{"value": [-0.08387792855501175], "step": 3}]}, "val_mean_squared_error": {"direction": "min", "observations": [{"value": [5622792704.0], "step": 3}]}, "val_mean_absolute_error": {"direction": "min", "observations": [{"value": [10703.7978515625], "step": 3}]}, "val_mean_absolute_percentage_error": {"direction": "min", "observations": [{"value": [143.98599243164062], "step": 3}]}, "val_mean_squared_logarithmic_error": {"direction": "min", "observations": [{"value": [1.6074515581130981], "step": 3}]}, "val_root_mean_squared_error": {"direction": "min", "observations": [{"value": [74985.28125], "step": 3}]}, "val_acc": {"direction": "max", "observations": [{"value": [0.0], "step": 3}]}, "multi_objective": {"direction": "min", "observations": [{"value": [5622792704.0], "step": 3}]}}}, "score": 5622792704.0, "best_step": 3, "status": "COMPLETED", "message": null}