{"trial_id": "0042", "hyperparameters": {"space": [{"class_name": "Int", "config": {"name": "intermediate_dim1", "default": null, "conditions": [], "min_value": 32, "max_value": 512, "step": 32, "sampling": "linear"}}, {"class_name": "Float", "config": {"name": "dropout1", "default": 0.1, "conditions": [], "min_value": 0.1, "max_value": 0.8, "step": null, "sampling": "log"}}, {"class_name": "Int", "config": {"name": "intermediate_dim2", "default": null, "conditions": [], "min_value": 32, "max_value": 512, "step": 32, "sampling": "linear"}}, {"class_name": "Float", "config": {"name": "dropout2", "default": 0.1, "conditions": [], "min_value": 0.1, "max_value": 0.8, "step": null, "sampling": "log"}}, {"class_name": "Int", "config": {"name": "intermediate_dim3", "default": null, "conditions": [], "min_value": 32, "max_value": 512, "step": 32, "sampling": "linear"}}, {"class_name": "Float", "config": {"name": "dropout3", "default": 0.1, "conditions": [], "min_value": 0.1, "max_value": 0.8, "step": null, "sampling": "log"}}, {"class_name": "Float", "config": {"name": "rate", "default": 0.1, "conditions": [], "min_value": 0.1, "max_value": 0.8, "step": null, "sampling": "log"}}, {"class_name": "Float", "config": {"name": "lr", "default": 0.0001, "conditions": [], "min_value": 0.0001, "max_value": 0.01, "step": null, "sampling": "log"}}, {"class_name": "Float", "config": {"name": "weight_decay", "default": 0.0001, "conditions": [], "min_value": 0.0001, "max_value": 0.01, "step": null, "sampling": "log"}}], "values": {"intermediate_dim1": 512, "dropout1": 0.7328729233752836, "intermediate_dim2": 32, "dropout2": 0.22435308241814247, "intermediate_dim3": 128, "dropout3": 0.21491757977081477, "rate": 0.23043127684638287, "lr": 0.0021963029380171572, "weight_decay": 0.00012782619210581372, "tuner/epochs": 4, "tuner/initial_epoch": 2, "tuner/bracket": 3, "tuner/round": 1, "tuner/trial_id": "0016"}}, "metrics": {"metrics": {"loss": {"direction": "min", "observations": [{"value": [2371584512.0], "step": 1}]}, "r2_score": {"direction": "min", "observations": [{"value": [-0.2284735143184662], "step": 1}]}, "mean_squared_error": {"direction": "min", "observations": [{"value": [2371584512.0], "step": 1}]}, "mean_absolute_error": {"direction": "min", "observations": [{"value": [12015.1689453125], "step": 1}]}, "mean_absolute_percentage_error": {"direction": "min", "observations": [{"value": [83.69723510742188], "step": 1}]}, "mean_squared_logarithmic_error": {"direction": "min", "observations": [{"value": [6.9934282302856445], "step": 1}]}, "root_mean_squared_error": {"direction": "min", "observations": [{"value": [48698.91796875], "step": 1}]}, "acc": {"direction": "max", "observations": [{"value": [0.0], "step": 1}]}, "val_loss": {"direction": "min", "observations": [{"value": [5693595136.0], "step": 1}]}, "val_r2_score": {"direction": "min", "observations": [{"value": [-0.2427985668182373], "step": 1}]}, "val_mean_squared_error": {"direction": "min", "observations": [{"value": [5693595136.0], "step": 1}]}, "val_mean_absolute_error": {"direction": "min", "observations": [{"value": [11838.6982421875], "step": 1}]}, "val_mean_absolute_percentage_error": {"direction": "min", "observations": [{"value": [78.85257720947266], "step": 1}]}, "val_mean_squared_logarithmic_error": {"direction": "min", "observations": [{"value": [5.6789445877075195], "step": 1}]}, "val_root_mean_squared_error": {"direction": "min", "observations": [{"value": [75455.9140625], "step": 1}]}, "val_acc": {"direction": "max", "observations": [{"value": [0.0], "step": 1}]}, "multi_objective": {"direction": "min", "observations": [{"value": [5693595136.0], "step": 1}]}}}, "score": 5693595136.0, "best_step": 1, "status": "COMPLETED", "message": null}